py_scripto/__init__.py
py_scripto/sqlserver.py
py_scripto-0.1.4.dist-info/LICENSE
py_scripto-0.1.4.dist-info/METADATA
py_scripto-0.1.4.dist-info/WHEEL
py_scripto-0.1.4.dist-info/top_level.txt
py_scripto-0.1.4.dist-info/RECORD
