Metadata-Version: 2.1
Name: py-scripto
Version: 0.1.4
Summary: A package to run SQL script or SQL file script in an instance of sql server
Home-page: https://github.com/datnguye/py_scripto
Author: datnguye
Author-email: datnguyen.it09@gmail.com
License: MIT
Platform: UNKNOWN
Requires-Python: >=3.7.5
Requires-Dist: pyodbc (==4.0.30)
